LICENSE
django_whatsapp_api_wrapper/__init__.py
django_whatsapp_api_wrapper/admin.py
django_whatsapp_api_wrapper/apps.py
django_whatsapp_api_wrapper/authentication/__init__.py
django_whatsapp_api_wrapper/authentication/api_key.py
django_whatsapp_api_wrapper/authentication/base.py
django_whatsapp_api_wrapper/client.py
django_whatsapp_api_wrapper/decorators.py
django_whatsapp_api_wrapper/embedded_signup/__init__.py
django_whatsapp_api_wrapper/embedded_signup/coexistence/README.md
django_whatsapp_api_wrapper/embedded_signup/coexistence/__init__.py
django_whatsapp_api_wrapper/embedded_signup/coexistence/serializers.py
django_whatsapp_api_wrapper/embedded_signup/coexistence/urls.py
django_whatsapp_api_wrapper/embedded_signup/coexistence/views.py
django_whatsapp_api_wrapper/embedded_signup/serializers.py
django_whatsapp_api_wrapper/embedded_signup/urls.py
django_whatsapp_api_wrapper/embedded_signup/views.py
django_whatsapp_api_wrapper/hooks.py
django_whatsapp_api_wrapper/management/__init__.py
django_whatsapp_api_wrapper/management/commands/__init__.py
django_whatsapp_api_wrapper/management/commands/process_waba_history_inbox.py
django_whatsapp_api_wrapper/management/commands/setup_whatsapp.py
django_whatsapp_api_wrapper/migrations/0001_initial.py
django_whatsapp_api_wrapper/migrations/0002_alter_whatsappcloudapibusiness_verify_token.py
django_whatsapp_api_wrapper/migrations/0003_metaapp.py
django_whatsapp_api_wrapper/migrations/0004_whatsappcloudapibusiness_code_and_more.py
django_whatsapp_api_wrapper/migrations/0005_webhooks_models.py
django_whatsapp_api_wrapper/migrations/0006_remove_whatsappembeddedsignup_business_and_more.py
django_whatsapp_api_wrapper/migrations/0007_remove_whatsappembeddedsignup_model.py
django_whatsapp_api_wrapper/migrations/0008_alter_webhookevent_event_kind_accountupdate.py
django_whatsapp_api_wrapper/migrations/0009_whatsappbusinessaccount_and_more.py
django_whatsapp_api_wrapper-0.16.0.dist-info/LICENSE
django_whatsapp_api_wrapper-0.16.0.dist-info/METADATA
django_whatsapp_api_wrapper-0.16.0.dist-info/WHEEL
django_whatsapp_api_wrapper-0.16.0.dist-info/RECORD
